agnipod/__init__.py
agnipod/main.py
agnipod-0.1.0.dist-info/METADATA
agnipod-0.1.0.dist-info/WHEEL
agnipod-0.1.0.dist-info/entry_points.txt
agnipod-0.1.0.dist-info/top_level.txt
agnipod-0.1.0.dist-info/RECORD
