Metadata-Version: 2.1
Name: agnipod
Version: 0.1.0
Author: Anuj Sangwan
Requires-Dist: requests >=2.25.1
